ftapp.py
ftapp-0.0.1.dist-info/LICENSE
ftapp-0.0.1.dist-info/METADATA
ftapp-0.0.1.dist-info/WHEEL
ftapp-0.0.1.dist-info/entry_points.txt
ftapp-0.0.1.dist-info/top_level.txt
ftapp-0.0.1.dist-info/RECORD
