Metadata-Version: 2.1
Name: ftapp
Version: 0.0.1
Summary: Script zur Erstellung einer fischertechnik Anwendung
Home-page: https://github.com/heuer/ftapp/
Author: Lars Heuer
Author-email: heuer@semagia.com
License: BSD
Keywords: fischertechnik,ftduino
Platform: any
Classifier: Development Status :: 4 - Beta
Classifier: Intended Audience :: Developers
Classifier: Intended Audience :: Education
Classifier: License :: OSI Approved :: BSD License
Classifier: Operating System :: OS Independent
Classifier: Programming Language :: Python
Classifier: Programming Language :: Python :: 2
Classifier: Programming Language :: Python :: 2.7
Classifier: Programming Language :: Python :: 3
Classifier: Topic :: Software Development :: Libraries :: Python Modules
Classifier: Topic :: Utilities
Requires-Dist: click (>=5.1)
